rxnfp/__init__.py
rxnfp/_nbdev.py
rxnfp/core.py
rxnfp/models.py
rxnfp/tokenization.py
rxnfp/transformer_fingerprints.py
rxnfp/models/transformers/bert_ft/config.json
rxnfp/models/transformers/bert_ft/pytorch_model.bin
rxnfp/models/transformers/bert_ft/vocab.txt
rxnfp/models/transformers/bert_ft_10k_25s/config.json
rxnfp/models/transformers/bert_ft_10k_25s/pytorch_model.bin
rxnfp/models/transformers/bert_ft_10k_25s/scheduler.pt
rxnfp/models/transformers/bert_ft_10k_25s/special_tokens_map.json
rxnfp/models/transformers/bert_ft_10k_25s/tokenizer_config.json
rxnfp/models/transformers/bert_ft_10k_25s/training_args.bin
rxnfp/models/transformers/bert_ft_10k_25s/vocab.txt
rxnfp/models/transformers/bert_pretrained/config.json
rxnfp/models/transformers/bert_pretrained/pytorch_model.bin
rxnfp/models/transformers/bert_pretrained/vocab.txt
rxnfp-0.1.0.dist-info/LICENSE
rxnfp-0.1.0.dist-info/METADATA
rxnfp-0.1.0.dist-info/WHEEL
rxnfp-0.1.0.dist-info/entry_points.txt
rxnfp-0.1.0.dist-info/top_level.txt
rxnfp-0.1.0.dist-info/RECORD
