Metadata-Version: 2.1
Name: rxnfp
Version: 0.1.0
Summary: chemical reaction fingerprints
Home-page: https://github.com/rxn4chemistry/rxnfp/tree/master/
Author: Philippe Schwaller
Author-email: phs@zurich.ibm.com
License: MIT License
Keywords: chemical reactions fingerprints classification
Platform: UNKNOWN
Classifier: Development Status :: 3 - Alpha
Classifier: Intended Audience :: Developers
Classifier: License :: OSI Approved :: MIT License
Classifier: Natural Language :: English
Classifier: Programming Language :: Python :: 3.6
Classifier: Programming Language :: Python :: 3.7
Classifier: Programming Language :: Python :: 3.8
Requires-Python: >=3.6
Requires-Dist: transformers (>=4.5.0)
Requires-Dist: torch (>=1.6)
Requires-Dist: scipy (==1.4.1)
Requires-Dist: scikit-learn (==0.23.1)
Requires-Dist: matplotlib (==3.2.2)
Requires-Dist: faerun (==0.3.20)
